pydantigraph/__init__.py
pydantigraph/base.py
pydantigraph/const.py
pydantigraph/field.py
pydantigraph/model.py
pydantigraph/namespace.py
pydantigraph/property.py
pydantigraph/types.py
pydantigraph-0.1.0.dist-info/LICENSE
pydantigraph-0.1.0.dist-info/METADATA
pydantigraph-0.1.0.dist-info/WHEEL
pydantigraph-0.1.0.dist-info/RECORD
